netbox/__init__.py
netbox/connection.py
netbox/dcim.py
netbox/exceptions.py
netbox/ipam.py
netbox/netbox.py
netbox/tenancy.py
netbox/virtualization.py
python_netbox-0.0.11.dist-info/DESCRIPTION.rst
python_netbox-0.0.11.dist-info/METADATA
python_netbox-0.0.11.dist-info/RECORD
python_netbox-0.0.11.dist-info/WHEEL
python_netbox-0.0.11.dist-info/metadata.json
python_netbox-0.0.11.dist-info/top_level.txt
