Metadata-Version: 2.0
Name: python-netbox
Version: 0.0.11
Summary: Python NetBox Client
Home-page: https://github.com/jagter/python-netbox
Author: Thomas van der Jagt
Author-email: thomas@tjrb.nl
License: UNKNOWN
Download-URL: https://github.com/jagter/python-netbox/releases/tag/0.0.11.tar.gz
Platform: UNKNOWN
Classifier: Programming Language :: Python :: 3
Classifier: Intended Audience :: System Administrators
Classifier: License :: OSI Approved :: Apache Software License
Classifier: Programming Language :: Python :: 3.6
Requires-Python: >=3
Requires-Dist: ipaddress
Requires-Dist: requests
